{
  "A0114": {
    "title": "IoT设备安全配置强制执行",
    "category": "TC01",
    "definition": "通过网络接入控制和自动化扫描，强制IoT设备满足最低安全标准才允许入网",
    "description": "从接入层阻止不安全设备成为僵尸网络节点。实施措施：部署NAC（网络接入控制）系统，设备入网前检查固件版本、密码强度、开放端口；使用802.1X认证，未通过安全检查的设备隔离到受限VLAN；定期扫描网络内设备，发现使用默认凭证、过期固件、不必要开放端口的设备并通知管理员；自动化修复工具推送安全配置（如关闭Telnet、强制密码修改）；对无法修复的设备强制断网。BitLyft等安全方案强调从部署阶段就实施安全配置。",
    "complexity": "中级",
    "limitation": "NAC部署和维护成本高；可能阻止合法设备入网，影响业务；自动修复可能与设备功能冲突；对已在网设备改造困难",
    "references": [
      {
        "title": "Securing IoT Devices Against Botnet Exploits",
        "link": "https://www.bitlyft.com/resources/securing-iot-devices-against-botnet-exploits"
      }
    ],
    "updated": "2026-06-16",
    "keywords": [
      "NAC",
      "安全配置",
      "接入控制",
      "自动扫描",
      "强制合规"
    ]
  }
}