{
  "R0185": {
    "title": "虚拟世界资产盗窃",
    "definition": "元宇宙中用户虚拟资产（装备、道具、货币、NFT等）被非法窃取或转移。",
    "description": "元宇宙中的虚拟资产具有真实经济价值，成为攻击者目标。盗窃手段包括：利用智能合约漏洞转移NFT资产、通过社会工程骗取钱包私钥、入侵游戏服务器窃取道具、利用交易系统漏洞复制资产、钓鱼网站诱导授权等。虚拟资产的数字化特性使其易被批量盗取和快速转移，且跨境追踪困难。",
    "complexity": "高级",
    "influence": "用户虚拟财产损失，元宇宙经济体系失衡，平台信誉受损。",
    "avoidances": [
      "A0152",
      "A0155",
      "A0156",
      "A0157",
      "A0104",
      "A0105",
      "A0095",
      "A0189"
    ],
    "references": [
      {
        "title": "Virtual Asset Security Best Practices",
        "link": "https://www.fatf-gafi.org/publications/fatfrecommendations/documents/guidance-rba-virtual-assets.html"
      }
    ],
    "updated": "2026-06-15",
    "keywords": [
      "虚拟世界资产盗窃",
      "虚拟资产盗窃",
      "NFT盗窃",
      "游戏资产盗窃",
      "虚拟货币盗窃",
      "数字财产",
      "virtual asset theft"
    ]
  }
}
