{
  "BS14": {
    "title": "人工智能",
    "description": "人工智能行业涵盖大语言模型服务、AI生成内容平台、智能客服、AI辅助决策、计算机视觉服务等业务场景，面临独特的业务安全风险。",
    "updated": "2026-06-17",
    "riskDimensions": {
      "RD01": {
        "title": "交易维度",
        "riskScenes": [
          "RS08"
        ],
        "updated": "2026-02-27"
      },
      "RD02": {
        "title": "运营维度",
        "riskScenes": [
          "RS02",
          "RS05",
          "RS06",
          "RS28",
          "RS26"
        ],
        "updated": "2026-02-27"
      },
      "RD03": {
        "title": "身份维度",
        "riskScenes": [
          "RS07",
          "RS09"
        ],
        "updated": "2026-02-27"
      },
      "RD04": {
        "title": "对抗维度",
        "riskScenes": [
          "RS04",
          "RS10",
          "RS14"
        ],
        "updated": "2026-02-27"
      },
      "RD05": {
        "title": "AI与数据维度",
        "riskScenes": [
          "RS13"
        ],
        "updated": "2026-02-27"
      }
    },
    "riskScenes": {
      "RS02": {
        "title": "合规与治理风险",
        "risks": [
          "R0074",
          "R0077",
          "R0078",
          "R0078-001",
          "R0123",
          "R0124",
          "R0155",
          "R0156",
          "R0157",
          "R0039",
          "R0020"
        ],
        "updated": "2026-02-27"
      },
      "RS04": {
        "title": "接口与自动化攻击",
        "risks": [
          "R0001",
          "R0001-001",
          "R0001-002",
          "R0027",
          "R0028",
          "R0029",
          "R0029-001",
          "R0029-002",
          "R0029-003",
          "R0029-004",
          "R0087",
          "R0109",
          "R0117",
          "R0117-001",
          "R0117-002",
          "R0118",
          "R0126",
          "R0126-001",
          "R0126-002",
          "R0126-003",
          "R0148"
        ],
        "updated": "2026-02-27"
      },
      "RS05": {
        "title": "内容与社区治理",
        "risks": [
          "R0020",
          "R0021",
          "R0022",
          "R0069",
          "R0069-001",
          "R0069-002",
          "R0071",
          "R0071-001",
          "R0071-002",
          "R0071-003",
          "R0071-004",
          "R0119",
          "R0130"
        ],
        "updated": "2026-02-27"
      },
      "RS06": {
        "title": "内部安全",
        "risks": [
          "R0059",
          "R0072",
          "R0072-001",
          "R0083",
          "R0083-001",
          "R0083-002",
          "R0111",
          "R0111-001",
          "R0111-002",
          "R0153",
          "R0158"
        ],
        "updated": "2026-06-17"
      },
      "RS28": {
        "title": "供应链安全",
        "risks": [
          "R0081",
          "R0081-001",
          "R0081-003",
          "R0081-005",
          "R0127",
          "R0128",
          "R0149"
        ],
        "updated": "2026-06-17"
      },
      "RS07": {
        "title": "账号接管与身份盗用",
        "risks": [
          "R0084",
          "R0032",
          "R0032-001",
          "R0032-002",
          "R0032-003",
          "R0032-004",
          "R0035",
          "R0035-001",
          "R0036",
          "R0036-001",
          "R0131",
          "R0132",
          "R0151",
          "R0154",
          "R0089",
          "R0090",
          "R0092",
          "R0116",
          "R0116-001",
          "R0116-002",
          "R0120",
          "R0214"
        ],
        "updated": "2026-02-27"
      },
      "RS08": {
        "title": "AI API计费、订阅与算力资源滥用",
        "risks": [
          "R0019",
          "R0040",
          "R0041",
          "R0043",
          "R0043-001",
          "R0062",
          "R0138",
          "R0140",
          "R0158"
        ],
        "updated": "2026-02-27"
      },
      "RS09": {
        "title": "注册、认证与账号黑产",
        "risks": [
          "R0030",
          "R0030-001",
          "R0030-002",
          "R0031",
          "R0047",
          "R0048",
          "R0088",
          "R0098",
          "R0136",
          "R0143"
        ],
        "updated": "2026-02-27"
      },
      "RS10": {
        "title": "AI终端透明度与客户端对抗",
        "risks": [
          "R0050",
          "R0050-001",
          "R0051",
          "R0051-001",
          "R0051-002",
          "R0099",
          "R0142",
          "R0157"
        ],
        "updated": "2026-02-27"
      },
      "RS13": {
        "title": "AI模型、智能体与数据安全",
        "risks": [
          "R0071",
          "R0071-001",
          "R0071-002",
          "R0071-003",
          "R0071-004",
          "R0071-005",
          "R0117",
          "R0117-001",
          "R0117-002",
          "R0118",
          "R0123",
          "R0126",
          "R0126-001",
          "R0126-002",
          "R0126-003",
          "R0148",
          "R0149",
          "R0153",
          "R0157",
          "R0158",
          "R0116",
          "R0120",
          "R0214",
          "R0242",
          "R0243",
          "R0244",
          "R0245"
        ],
        "updated": "2026-06-17"
      },
      "RS14": {
        "title": "API、云原生与非人类身份安全",
        "risks": [
          "R0126",
          "R0126-001",
          "R0126-002",
          "R0126-003",
          "R0128",
          "R0149"
        ],
        "updated": "2026-02-27"
      },
      "RS26": {
        "title": "算法、定价与平台治理",
        "risks": [
          "R0123",
          "R0124",
          "R0156",
          "R0157"
        ],
        "updated": "2026-02-27"
      }
    },
    "risks": []
  }
}
