{
  "T0354": {
    "title": "水房",
    "keywords": [
      "水房",
      "洗钱窝点",
      "资金分流",
      "跑分",
      "地下钱庄",
      "多级转账",
      "赌资洗白",
      "资金归集",
      "水房转账"
    ],
    "aliases": [],
    "category": "赌博",
    "definition": "专门处理赌资流转和洗钱的窝点或团伙。",
    "description": "水房承接赌场或网赌平台的资金分流任务，通过多级账户快速拆分、归集赌资，切断资金溯源路径。操作人员使用大量他人账户进行高频转账，最终将资金洗白后回流给幕后庄家。一旦被查，水房往往是整个资金链中最先暴露的节点。",
    "relatedRisks": [
      "R0097",
      "R0060"
    ],
    "relatedAvoidances": [
      "A0015",
      "A0016",
      "A0044",
      "A0061",
      "A0024",
      "A0054"
    ],
    "relatedAttackTools": [
      "AT0026"
    ],
    "relatedThreatActors": [
      "TA0038",
      "TA0006-003",
      "TA0014",
      "TA0016"
    ],
    "relatedBusinessScenes": [
      "BS06",
      "BS01"
    ],
    "references": [
      {
        "title": "【黑产大数据】2025年上半年互联网黑灰产趋势半年度总结",
        "link": "https://www.threathunter.cn/blog/2025-h1-anti-fraud-intelligence"
      },
      {
        "title": "【黑产大数据】2025年互联网黑灰产趋势年度总结",
        "link": "https://www.163.com/dy/article/KJ2QH6LE0518STKV.html"
      }
    ],
    "updated": "2026-06-16"
  }
}
